MANIFEST.in
README.MD
setup.py
requirements/development.txt
requirements/setup.txt
src/django_dde.egg-info/PKG-INFO
src/django_dde.egg-info/SOURCES.txt
src/django_dde.egg-info/dependency_links.txt
src/django_dde.egg-info/requires.txt
src/django_dde.egg-info/top_level.txt
src/django_dde.egg-info/zip-safe
src/exporter/__init__.py
src/exporter/apps.py
src/exporter/exceptions.py
src/exporter/handlers.py
src/exporter/managers.py
src/exporter/models.py
src/exporter/signals.py
src/exporter/tasks.py
src/exporter/utils.py