Metadata-Version: 2.1
Name: django-dde
Version: 0.1.5
Summary: Asynchronous and Distributed Data Exporter from a Django QuerySet
Home-page: https://github.com/stored/django-dde
Author: Stored
Author-email: dev@stored.com.br
License: UNKNOWN
Platform: UNKNOWN
Provides-Extra: tests
